{
  "$schema": "https://github.com/zhbcher/pentovideo/schema/registry-item.json",
  "name": "shimmer-sweep",
  "type": "pentovideo:component",
  "title": "Shimmer Sweep",
  "description": "Animated light sweep across text or elements using a CSS gradient mask — ideal for AI accents and premium reveals",
  "tags": ["text", "shimmer", "highlight", "effect"],
  "files": [
    {
      "path": "shimmer-sweep.html",
      "target": "compositions/components/shimmer-sweep.html",
      "type": "pentovideo:snippet"
    }
  ]
}
