{
  "$schema": "https://github.com/zhbcher/pentovideo/schema/registry-item.json",
  "name": "cross-warp-morph",
  "type": "pentovideo:block",
  "title": "Cross Warp Morph",
  "description": "Shader transition with cross-warped morphing",
  "tags": ["transition", "shader"],
  "dimensions": {
    "width": 1920,
    "height": 1080
  },
  "duration": 4,
  "files": [
    {
      "path": "cross-warp-morph.html",
      "target": "compositions/cross-warp-morph.html",
      "type": "pentovideo:composition"
    }
  ]
}
